{
  "id": 1614,
  "name": {
    "zh_tw": "礦石魔",
    "en": "MINERAL"
  },
  "image_url": "/images/monsters/1614.gif",
  "basic_info": {
    "level": 96,
    "race": "無形",
    "element": {
      "type": "無",
      "level": 2
    },
    "size": "小"
  },
  "stats": {
    "hp": 8300,
    "attack": {
      "min": 766,
      "max": 1068
    },
    "magic_attack": {
      "min": 185,
      "max": 221
    },
    "defense": 127,
    "magic_defense": 23,
    "hit_100_percent": 367,
    "flee_95_percent": 0,
    "base_stats": {
      "str": 70,
      "agi": 61,
      "vit": 40,
      "int": 50,
      "dex": 74,
      "luk": 50
    }
  },
  "drops": [
    {
      "item_id": 714,
      "name": "華麗金屬",
      "rate": 0.01,
      "icon_url": "/images/items/714.gif"
    },
    {
      "item_id": 715,
      "name": "黃色魔力礦石",
      "rate": 0.5,
      "icon_url": "/images/items/715.gif"
    },
    {
      "item_id": 728,
      "name": "黃寶石",
      "rate": 2.5,
      "icon_url": "/images/items/728.gif"
    },
    {
      "item_id": 969,
      "name": "黃金",
      "rate": 0.01,
      "icon_url": "/images/items/969.gif"
    },
    {
      "item_id": 984,
      "name": "神之金屬",
      "rate": 0.4,
      "icon_url": "/images/items/984.gif"
    },
    {
      "item_id": 1011,
      "name": "強化武器金屬-級數二",
      "rate": 4.0,
      "icon_url": "/images/items/1011.gif"
    },
    {
      "item_id": 4339,
      "name": "礦石魔卡片",
      "rate": 0.01,
      "icon_url": "/images/items/card.gif"
    },
    {
      "item_id": 7321,
      "name": "水晶碎片",
      "rate": 15.0,
      "icon_url": "/images/items/7321.gif"
    }
  ]
}