{
  "id": 1616,
  "name": {
    "zh_tw": "礦工魔",
    "en": "PITMAN"
  },
  "image_url": "/images/monsters/1616.gif",
  "basic_info": {
    "level": 0,
    "race": "不死",
    "element": {
      "type": "地",
      "level": 2
    },
    "size": "大"
  },
  "stats": {
    "hp": 7208,
    "attack": {
      "min": 328,
      "max": 408
    },
    "magic_attack": {
      "min": 167,
      "max": 203
    },
    "defense": 104,
    "magic_defense": 48,
    "hit_100_percent": 352,
    "flee_95_percent": 330,
    "base_stats": {
      "str": 78,
      "agi": 56,
      "vit": 45,
      "int": 35,
      "dex": 60,
      "luk": 30
    }
  },
  "spawns": [
    {
      "map_name": "ein_dun01",
      "description": "- 礦山洞穴 1層",
      "spawn_info": "70x / 5 秒"
    },
    {
      "map_name": "ein_fild03",
      "description": "- 艾音布羅克 原野",
      "spawn_info": "20x / 5 秒"
    },
    {
      "map_name": "ein_fild04",
      "description": "- 艾音布羅克 原野",
      "spawn_info": "12x / 5 秒"
    },
    {
      "map_name": "ein_fild05",
      "description": "- 艾音布羅克 原野",
      "spawn_info": "10x / 5 秒"
    }
  ],
  "drops": [
    {
      "item_id": 999,
      "name": "鋼鐵",
      "rate": 2.5,
      "icon_url": "/images/items/999.gif"
    },
    {
      "item_id": 1003,
      "name": "煤礦",
      "rate": 0.5,
      "icon_url": "/images/items/1003.gif"
    },
    {
      "item_id": 1041,
      "name": "手提燈",
      "rate": 5.0,
      "icon_url": "/images/items/1041.gif"
    },
    {
      "item_id": 4335,
      "name": "礦工魔卡片",
      "rate": 0.01,
      "icon_url": "/images/items/card.gif"
    },
    {
      "item_id": 6244,
      "name": "火藥粉末",
      "rate": 4.5,
      "icon_url": "/images/items/6244.gif"
    },
    {
      "item_id": 7318,
      "name": "老舊的十字鎬",
      "rate": 15.0,
      "icon_url": "/images/items/7318.gif"
    },
    {
      "item_id": 7319,
      "name": "老舊的鐵板",
      "rate": 2.5,
      "icon_url": "/images/items/7319.gif"
    },
    {
      "item_id": 7327,
      "name": "懷中電燈",
      "rate": 0.4,
      "icon_url": "/images/items/7327.gif"
    }
  ]
}