{
  "id": 1634,
  "name": {
    "zh_tw": "暗●騎士領主",
    "en": "SEYREN"
  },
  "image_url": "/images/monsters/1634.gif",
  "basic_info": {
    "level": 0,
    "race": "惡魔",
    "element": {
      "type": "火",
      "level": 3
    },
    "size": "中"
  },
  "stats": {
    "hp": 204962,
    "attack": {
      "min": 3108,
      "max": 4510
    },
    "magic_attack": {
      "min": 1112,
      "max": 1904
    },
    "defense": 166,
    "magic_defense": 12,
    "hit_100_percent": 452,
    "flee_95_percent": 528,
    "base_stats": {
      "str": 162,
      "agi": 99,
      "vit": 186,
      "int": 49,
      "dex": 198,
      "luk": 55
    }
  },
  "spawns": [
    {
      "map_name": "4@tower",
      "description": "- 無限塔 (魔物終結塔) 4樓",
      "spawn_info": ""
    },
    {
      "map_name": "lhz_dun03",
      "description": "- 生體試驗 研究所 地下3樓",
      "spawn_info": "42x / 5 秒"
    }
  ],
  "drops": [
    {
      "item_id": 4358,
      "name": "暗●騎士領主卡片",
      "rate": 0.01,
      "icon_url": "/images/items/card.gif"
    },
    {
      "item_id": 6223,
      "name": "混沌金屬",
      "rate": 0.01,
      "icon_url": "/images/items/6223.gif"
    },
    {
      "item_id": 6469,
      "name": "勇士的意志",
      "rate": 2.0,
      "icon_url": "/images/items/6469.gif"
    },
    {
      "item_id": 6471,
      "name": "亡者的寒氣",
      "rate": 0.01,
      "icon_url": "/images/items/6471.gif"
    },
    {
      "item_id": 7345,
      "name": "犯人的手煉",
      "rate": 15.0,
      "icon_url": "/images/items/7345.gif"
    },
    {
      "item_id": 13001,
      "name": "天龍短劍",
      "rate": 0.01,
      "icon_url": "/images/items/13001.gif"
    },
    {
      "item_id": 13421,
      "name": "火紅單手劍[1]",
      "rate": 1.0,
      "icon_url": "/images/items/13421.gif"
    },
    {
      "item_id": 25129,
      "name": "不安的能量碎片",
      "rate": 10.0,
      "icon_url": "/images/items/25129.gif"
    }
  ]
}