{
  "id": 1789,
  "name": {
    "zh_tw": "冰柱",
    "en": "ICEICLE"
  },
  "image_url": "/images/monsters/1789.gif",
  "basic_info": {
    "level": 0,
    "race": "無形",
    "element": {
      "type": "水",
      "level": 2
    },
    "size": "小"
  },
  "stats": {
    "hp": 1012,
    "attack": {
      "min": 641,
      "max": 863
    },
    "magic_attack": {
      "min": 101,
      "max": 103
    },
    "defense": 2,
    "magic_defense": 15,
    "hit_100_percent": 301,
    "flee_95_percent": 464,
    "base_stats": {
      "str": 99,
      "agi": 1,
      "vit": 1,
      "int": 1,
      "dex": 194,
      "luk": 1
    }
  },
  "spawns": [
    {
      "map_name": "ice_dun02",
      "description": "- 拉赫 冰洞穴 2層",
      "spawn_info": "19x / 5 秒"
    },
    {
      "map_name": "ice_dun03",
      "description": "- 拉赫 冰洞穴 3層",
      "spawn_info": "32x / 5 秒"
    }
  ],
  "drops": [
    {
      "item_id": 6257,
      "name": "冰結晶",
      "rate": 2.5,
      "icon_url": "/images/items/6257.gif"
    },
    {
      "item_id": 7066,
      "name": "冰塊一角",
      "rate": 5.0,
      "icon_url": "/images/items/7066.gif"
    },
    {
      "item_id": 7066,
      "name": "冰塊一角",
      "rate": 5.0,
      "icon_url": "/images/items/7066.gif"
    },
    {
      "item_id": 7066,
      "name": "冰塊一角",
      "rate": 2.5,
      "icon_url": "/images/items/7066.gif"
    },
    {
      "item_id": 7066,
      "name": "冰塊一角",
      "rate": 2.5,
      "icon_url": "/images/items/7066.gif"
    },
    {
      "item_id": 7066,
      "name": "冰塊一角",
      "rate": 2.5,
      "icon_url": "/images/items/7066.gif"
    },
    {
      "item_id": 7066,
      "name": "冰塊一角",
      "rate": 2.5,
      "icon_url": "/images/items/7066.gif"
    },
    {
      "item_id": 7066,
      "name": "冰塊一角",
      "rate": 2.5,
      "icon_url": "/images/items/7066.gif"
    }
  ]
}