{
  "id": 1981,
  "name": {
    "zh_tw": "獸人守護隊長",
    "en": "I_HIGH_ORC"
  },
  "image_url": "/images/monsters/1981.gif",
  "basic_info": {
    "level": 0,
    "race": "人形",
    "element": {
      "type": "火",
      "level": 2
    },
    "size": "大"
  },
  "stats": {
    "hp": 44193,
    "attack": {
      "min": 586,
      "max": 802
    },
    "magic_attack": {
      "min": 217,
      "max": 307
    },
    "defense": 101,
    "magic_defense": 45,
    "hit_100_percent": 301,
    "flee_95_percent": 340,
    "base_stats": {
      "str": 75,
      "agi": 16,
      "vit": 40,
      "int": 31,
      "dex": 83,
      "luk": 20
    }
  },
  "spawns": [
    {
      "map_name": "2@orcs",
      "description": "- 獸人地下洞穴 2樓",
      "spawn_info": ""
    }
  ],
  "drops": []
}