{
  "id": 2020,
  "name": {
    "zh_tw": "鉤藤",
    "en": "RHYNCHO"
  },
  "image_url": "/images/monsters/2020.gif",
  "basic_info": {
    "level": 139,
    "race": "無形",
    "element": {
      "type": "水",
      "level": 3
    },
    "size": "中"
  },
  "stats": {
    "hp": 337220,
    "attack": {
      "min": 948,
      "max": 1294
    },
    "magic_attack": {
      "min": 327,
      "max": 449
    },
    "defense": 68,
    "magic_defense": 12,
    "hit_100_percent": 446,
    "flee_95_percent": 443,
    "base_stats": {
      "str": 119,
      "agi": 98,
      "vit": 62,
      "int": 48,
      "dex": 119,
      "luk": 46
    }
  },
  "spawns": [
    {
      "map_name": "1@nyd",
      "description": "- 尼德霍格巢穴 1樓",
      "spawn_info": ""
    },
    {
      "map_name": "2@nyd",
      "description": "- 尼德霍格巢穴 1樓",
      "spawn_info": ""
    }
  ],
  "drops": [
    {
      "item_id": 972,
      "name": "卡勒波迪藥水",
      "rate": 0.03,
      "icon_url": "/images/items/972.gif"
    },
    {
      "item_id": 4460,
      "name": "靈克卡片",
      "rate": 0.01,
      "icon_url": "/images/items/card.gif"
    },
    {
      "item_id": 6087,
      "name": "藍色精靈結晶",
      "rate": 2.5,
      "icon_url": "/images/items/6087.gif"
    },
    {
      "item_id": 7326,
      "name": "熒光色的液體",
      "rate": 25.0,
      "icon_url": "/images/items/7326.gif"
    }
  ]
}