{
  "id": 2415,
  "name": {
    "zh_tw": "暗●騎士",
    "en": "L_SEYREN"
  },
  "image_url": "/images/monsters/2415.gif",
  "basic_info": {
    "level": 0,
    "race": "人形",
    "element": {
      "type": "火",
      "level": 3
    },
    "size": "中"
  },
  "stats": {
    "hp": 13260,
    "attack": {
      "min": 886,
      "max": 1218
    },
    "magic_attack": {
      "min": 341,
      "max": 513
    },
    "defense": 149,
    "magic_defense": 10,
    "hit_100_percent": 369,
    "flee_95_percent": 402,
    "base_stats": {
      "str": 127,
      "agi": 62,
      "vit": 77,
      "int": 44,
      "dex": 118,
      "luk": 49
    }
  },
  "spawns": [
    {
      "map_name": "teg_dun01",
      "description": "- TE 公會地下迷宮",
      "spawn_info": "20x / 5 秒"
    }
  ],
  "drops": [
    {
      "item_id": 603,
      "name": "神祕箱子",
      "rate": 0.02,
      "icon_url": "/images/items/603.gif"
    },
    {
      "item_id": 1163,
      "name": "十字巨劍",
      "rate": 0.5,
      "icon_url": "/images/items/1163.gif"
    },
    {
      "item_id": 1164,
      "name": "名刀 不知火",
      "rate": 0.05,
      "icon_url": "/images/items/1164.gif"
    },
    {
      "item_id": 2314,
      "name": "鋼鐵鎖子甲",
      "rate": 0.2,
      "icon_url": "/images/items/2314.gif"
    },
    {
      "item_id": 2315,
      "name": "鋼鐵鎖子甲[1]",
      "rate": 0.05,
      "icon_url": "/images/items/2315.gif"
    },
    {
      "item_id": 7345,
      "name": "犯人的手煉",
      "rate": 50.0,
      "icon_url": "/images/items/7345.gif"
    },
    {
      "item_id": 7347,
      "name": "研究員紀錄表",
      "rate": 25.0,
      "icon_url": "/images/items/7347.gif"
    }
  ]
}