{
  "id": 2485,
  "name": {
    "zh_tw": "凱美拉-咪魘",
    "en": "NG_CHIMERA"
  },
  "image_url": "images/monsters/2485.gif",
  "basic_info": {
    "level": 140,
    "race": "動物",
    "element": {
      "type": "火",
      "level": 3
    },
    "size": "大"
  },
  "stats": {
    "hp": 528120,
    "attack": {
      "min": 1887,
      "max": 2711
    },
    "magic_attack": {
      "min": 523,
      "max": 701
    },
    "defense": 159,
    "magic_defense": 20,
    "hit_100_percent": 450,
    "flee_95_percent": 548,
    "base_stats": {
      "str": 101,
      "agi": 76,
      "vit": 110,
      "int": 176,
      "dex": 182,
      "luk": 170
    }
  },
  "spawns": [
    {
      "map_name": "gl_cas02_",
      "description": "- 克雷斯特漢姆古城 地上樓層 2樓 (噩咪模式)",
      "spawn_info": ""
    }
  ],
  "drops": [
    {
      "item_id": 568,
      "name": "檸檬",
      "rate": 10.0,
      "icon_url": "images/items/568.gif"
    },
    {
      "item_id": 984,
      "name": "神之金屬",
      "rate": 1.5,
      "icon_url": "images/items/984.gif"
    },
    {
      "item_id": 1048,
      "name": "蛇發",
      "rate": 25.0,
      "icon_url": "images/items/1048.gif"
    },
    {
      "item_id": 1306,
      "name": "血腥戰斧[1]",
      "rate": 0.05,
      "icon_url": "images/items/1306.gif"
    },
    {
      "item_id": 1364,
      "name": "克萊伊特斧",
      "rate": 0.05,
      "icon_url": "images/items/1364.gif"
    },
    {
      "item_id": 4300,
      "name": "凱美拉卡片",
      "rate": 0.01,
      "icon_url": "images/items/card.gif"
    },
    {
      "item_id": 7054,
      "name": "布里刊",
      "rate": 50.0,
      "icon_url": "images/items/7054.gif"
    },
    {
      "item_id": 7295,
      "name": "黃水晶",
      "rate": 15.0,
      "icon_url": "images/items/7295.gif"
    }
  ]
}