{
  "id": 3212,
  "name": {
    "zh_tw": "暗●機匠 / 暗●機械工匠",
    "en": "V_HARWORD"
  },
  "image_url": "/images/monsters/3212.gif",
  "basic_info": {
    "level": 177,
    "race": "人形",
    "element": {
      "type": "水",
      "level": 4
    },
    "size": "中"
  },
  "stats": {
    "hp": 2720000,
    "attack": {
      "min": 3003,
      "max": 4337
    },
    "magic_attack": {
      "min": 1637,
      "max": 2837
    },
    "defense": 200,
    "magic_defense": 100,
    "hit_100_percent": 467,
    "flee_95_percent": 0,
    "base_stats": {
      "str": 160,
      "agi": 80,
      "vit": 200,
      "int": 60,
      "dex": 130,
      "luk": 50
    }
  },
  "drops": [
    {
      "item_id": 4688,
      "name": "真●機匠卡片",
      "rate": 0.01,
      "icon_url": "/images/items/card.gif"
    },
    {
      "item_id": 6815,
      "name": "商人之魂",
      "rate": 5.0,
      "icon_url": "/images/items/6815.gif"
    },
    {
      "item_id": 19963,
      "name": "(時裝)螺絲起子發夾(紅)",
      "rate": 0.5,
      "icon_url": "/images/items/19963.gif"
    },
    {
      "item_id": 19964,
      "name": "(時裝)螺絲起子發夾(黃)",
      "rate": 0.5,
      "icon_url": "/images/items/19964.gif"
    },
    {
      "item_id": 22687,
      "name": "邪念碎片",
      "rate": 6.0,
      "icon_url": "/images/items/22687.gif"
    },
    {
      "item_id": 23016,
      "name": "怨念碎片",
      "rate": 4.0,
      "icon_url": "/images/items/23016.gif"
    },
    {
      "item_id": 23016,
      "name": "怨念碎片",
      "rate": 2.0,
      "icon_url": "/images/items/23016.gif"
    },
    {
      "item_id": 25131,
      "name": "墮落的能量碎片",
      "rate": 10.0,
      "icon_url": "/images/items/25131.gif"
    }
  ]
}