{
  "id": 1127,
  "name": {
    "zh_tw": "蚯蚓",
    "en": "HODE"
  },
  "image_url": "/images/monsters/1127.gif",
  "basic_info": {
    "level": 63,
    "race": "動物",
    "element": {
      "type": "地",
      "level": 2
    },
    "size": "中"
  },
  "stats": {
    "hp": 2676,
    "attack": {
      "min": 267,
      "max": 339
    },
    "magic_attack": {
      "min": 99,
      "max": 127
    },
    "defense": 91,
    "magic_defense": 24,
    "hit_100_percent": 287,
    "flee_95_percent": 0,
    "base_stats": {
      "str": 61,
      "agi": 16,
      "vit": 42,
      "int": 5,
      "dex": 32,
      "luk": 40
    }
  },
  "drops": []
}