{
  "id": 1389,
  "name": {
    "zh_tw": "德古拉男爵",
    "en": "DRACULA"
  },
  "image_url": "/images/monsters/1389.gif",
  "basic_info": {
    "level": 75,
    "race": "惡魔",
    "element": {
      "type": "暗",
      "level": 4
    },
    "size": "大"
  },
  "stats": {
    "hp": 350000,
    "attack": {
      "min": 2124,
      "max": 3106
    },
    "magic_attack": {
      "min": 1435,
      "max": 2523
    },
    "defense": 252,
    "magic_defense": 146,
    "hit_100_percent": 390,
    "flee_95_percent": 0,
    "base_stats": {
      "str": 86,
      "agi": 99,
      "vit": 88,
      "int": 92,
      "dex": 194,
      "luk": 82
    }
  },
  "drops": []
}