{
  "id": 1513,
  "name": {
    "zh_tw": "狐仙",
    "en": "CIVIL_SERVANT"
  },
  "image_url": "/images/monsters/1513.gif",
  "basic_info": {
    "level": 89,
    "race": "動物",
    "element": {
      "type": "風",
      "level": 2
    },
    "size": "中"
  },
  "stats": {
    "hp": 5292,
    "attack": {
      "min": 399,
      "max": 521
    },
    "magic_attack": {
      "min": 196,
      "max": 234
    },
    "defense": 90,
    "magic_defense": 56,
    "hit_100_percent": 371,
    "flee_95_percent": 0,
    "base_stats": {
      "str": 67,
      "agi": 76,
      "vit": 40,
      "int": 65,
      "dex": 74,
      "luk": 30
    }
  },
  "drops": []
}