{
  "id": 20346,
  "name": {
    "zh_tw": "米古爾",
    "en": "MD_MIGUEL"
  },
  "image_url": "/images/monsters/20346.gif",
  "basic_info": {
    "level": 115,
    "race": "人形",
    "element": {
      "type": "風",
      "level": 4
    },
    "size": "中"
  },
  "stats": {
    "hp": 8600000,
    "attack": {
      "min": 3787,
      "max": 5527
    },
    "magic_attack": {
      "min": 1896,
      "max": 3366
    },
    "defense": 216,
    "magic_defense": 95,
    "hit_100_percent": 447,
    "flee_95_percent": 0,
    "base_stats": {
      "str": 192,
      "agi": 115,
      "vit": 28,
      "int": 66,
      "dex": 179,
      "luk": 85
    }
  },
  "drops": []
}