{
  "id": 2801,
  "name": {
    "zh_tw": "精英異形 / 菁英異形",
    "en": "C3_HODREMLIN"
  },
  "image_url": "/images/monsters/2801.gif",
  "basic_info": {
    "level": 122,
    "race": "惡魔",
    "element": {
      "type": "暗",
      "level": 3
    },
    "size": "中"
  },
  "stats": {
    "hp": 115910,
    "attack": {
      "min": 1144,
      "max": 1604
    },
    "magic_attack": {
      "min": 289,
      "max": 383
    },
    "defense": 75,
    "magic_defense": 25,
    "hit_100_percent": 400,
    "flee_95_percent": 0,
    "base_stats": {
      "str": 106,
      "agi": 70,
      "vit": 77,
      "int": 60,
      "dex": 83,
      "luk": 40
    }
  },
  "drops": []
}