{
  "id": 3631,
  "name": {
    "zh_tw": "人型凱美拉",
    "en": "EP16_2_HUMAN_KIMERA"
  },
  "image_url": "/images/monsters/3631.gif",
  "basic_info": {
    "level": 100,
    "race": "動物",
    "element": {
      "type": "無",
      "level": 2
    },
    "size": "中"
  },
  "stats": {
    "hp": 36968,
    "attack": {
      "min": 1302,
      "max": 1880
    },
    "magic_attack": {
      "min": 344,
      "max": 470
    },
    "defense": 80,
    "magic_defense": 100,
    "hit_100_percent": 350,
    "flee_95_percent": 0,
    "base_stats": {
      "str": 50,
      "agi": 50,
      "vit": 100,
      "int": 100,
      "dex": 140,
      "luk": 1
    }
  },
  "drops": []
}